Metadata-Version: 1.1
Name: ITSNOTME
Version: 1.0.7
Summary: ITSNOTME
Home-page: UNKNOWN
Author: ITSNOTME
Author-email: armannikoopour@gmail.com
License: MIT
Keywords: ITSNOTME
Platform: UNKNOWN
Classifier: Development Status :: 5 - Production/Stable
Classifier: Intended Audience :: Education
Classifier: Operating System :: Microsoft :: Windows :: Windows 10
Classifier: License :: OSI Approved :: MIT License
Classifier: Programming Language :: Python :: 3
